{
	"name": "event_Bash",
	"events": [
		{
			"eventType": "block",
			"conditions": [
				{
					"id": "key-is-down",
					"objectClass": "Keyboard",
					"sid": 897199329498297,
					"parameters": {
						"key": 37
					}
				},
				{
					"id": "key-is-down",
					"objectClass": "Keyboard",
					"sid": 427034566230279,
					"parameters": {
						"key": 39
					},
					"isInverted": true
				}
			],
			"actions": [
				{
					"id": "set-mirrored",
					"objectClass": "spr_bashy",
					"sid": 804771226263312,
					"parameters": {
						"state": "mirrored"
					}
				}
			],
			"sid": 769075085898959
		},
		{
			"eventType": "block",
			"conditions": [
				{
					"id": "key-is-down",
					"objectClass": "Keyboard",
					"sid": 692724432125860,
					"parameters": {
						"key": 39
					}
				},
				{
					"id": "key-is-down",
					"objectClass": "Keyboard",
					"sid": 139409090114749,
					"parameters": {
						"key": 37
					},
					"isInverted": true
				}
			],
			"actions": [
				{
					"id": "set-mirrored",
					"objectClass": "spr_bashy",
					"sid": 367889703592824,
					"parameters": {
						"state": "not-mirrored"
					}
				}
			],
			"sid": 691418820106581
		},
		{
			"eventType": "block",
			"conditions": [
				{
					"id": "is-moving",
					"objectClass": "spr_bashy",
					"sid": 111980276005741,
					"behaviorType": "Platform"
				},
				{
					"id": "is-on-floor",
					"objectClass": "spr_bashy",
					"sid": 342947028265764,
					"behaviorType": "Platform"
				},
				{
					"id": "is-animation-playing",
					"objectClass": "spr_bashy",
					"sid": 354053233614221,
					"parameters": {
						"animation": "\"Bash\""
					},
					"isInverted": true
				},
				{
					"id": "compare-speed",
					"objectClass": "spr_bashy",
					"sid": 883817967531826,
					"behaviorType": "Platform",
					"parameters": {
						"comparison": 4,
						"speed": "300"
					}
				}
			],
			"actions": [
				{
					"id": "set-animation",
					"objectClass": "spr_bashy",
					"sid": 863558132610784,
					"parameters": {
						"animation": "\"Run\"",
						"from": "beginning"
					}
				}
			],
			"sid": 134040195352824
		},
		{
			"eventType": "block",
			"conditions": [
				{
					"id": "is-on-floor",
					"objectClass": "spr_bashy",
					"sid": 246669001953145,
					"behaviorType": "Platform"
				},
				{
					"id": "is-animation-playing",
					"objectClass": "spr_bashy",
					"sid": 458938495313282,
					"parameters": {
						"animation": "\"Bash\""
					},
					"isInverted": true
				},
				{
					"id": "is-moving",
					"objectClass": "spr_bashy",
					"sid": 758662678567750,
					"behaviorType": "Platform",
					"isInverted": true
				}
			],
			"actions": [
				{
					"id": "set-animation",
					"objectClass": "spr_bashy",
					"sid": 289224872647096,
					"parameters": {
						"animation": "\"Default\"",
						"from": "beginning"
					}
				}
			],
			"sid": 738961029508473
		},
		{
			"eventType": "block",
			"conditions": [
				{
					"id": "on-jump",
					"objectClass": "spr_bashy",
					"sid": 362397908791763,
					"behaviorType": "Platform"
				}
			],
			"actions": [
				{
					"id": "play",
					"objectClass": "Audio",
					"sid": 313918871476289,
					"parameters": {
						"audio-file": "jump",
						"loop": "not-looping",
						"volume": "-10",
						"tag-optional": "\"\""
					}
				},
				{
					"id": "set-animation",
					"objectClass": "spr_bashy",
					"sid": 791652503963772,
					"parameters": {
						"animation": "\"Jump\"",
						"from": "beginning"
					}
				}
			],
			"sid": 522389965832238
		},
		{
			"eventType": "block",
			"conditions": [
				{
					"id": "key-is-down",
					"objectClass": "Keyboard",
					"sid": 554318331663135,
					"parameters": {
						"key": 32
					}
				}
			],
			"actions": [
				{
					"id": "set-animation",
					"objectClass": "spr_bashy",
					"sid": 814862869458467,
					"parameters": {
						"animation": "\"Bash\"",
						"from": "beginning"
					}
				}
			],
			"sid": 627380556987463
		}
	],
	"sid": 808825524418463
}